LICENSE
MANIFEST.in
README.rst
ebstall-pki.sh
ebstall-privspace.sh
ebstall.sh
setup.cfg
setup.py
ebstall/__init__.py
ebstall/audit.py
ebstall/cli.py
ebstall/clibase.py
ebstall/clirouter.py
ebstall/clivpn.py
ebstall/config.py
ebstall/core.py
ebstall/dbutil.py
ebstall/ebsysconfig.py
ebstall/errors.py
ebstall/osutil.py
ebstall/registration.py
ebstall/sysctlparser.py
ebstall/updater.py
ebstall/util.py
ebstall/versions.py
ebstall/watcher.py
ebstall.egg-info/PKG-INFO
ebstall.egg-info/SOURCES.txt
ebstall.egg-info/dependency_links.txt
ebstall.egg-info/entry_points.txt
ebstall.egg-info/requires.txt
ebstall.egg-info/top_level.txt
ebstall/consts/__init__.py
ebstall/consts/dnsmasq.conf
ebstall/consts/eb-init.sh
ebstall/consts/eb-systemd.conf
ebstall/consts/epiper.sh
ebstall/consts/nextcloud-trusteddomains.php
ebstall/consts/nginx-nextcloud.conf
ebstall/consts/ovpn-server.conf
ebstall/consts/pspace.env
ebstall/consts/supervisor-init.sh
ebstall/consts/supervisor-systemd.sh
ebstall/deployers/__init__.py
ebstall/deployers/certbot.py
ebstall/deployers/certificates.py
ebstall/deployers/dnsmasq.py
ebstall/deployers/ejabberd.py
ebstall/deployers/ejbca.py
ebstall/deployers/jboss.py
ebstall/deployers/letsencrypt.py
ebstall/deployers/mysql.py
ebstall/deployers/nextcloud.py
ebstall/deployers/nginx.py
ebstall/deployers/openvpn.py
ebstall/deployers/php.py
ebstall/deployers/pspace_web.py
ebstall/deployers/softhsm.py
ebstall/deployers/supervisord.py
ebstall/deployers/vpnauth.py
ebstall/tests/__init__.py
ebstall/tests/test.py
ebstall/tests/test_openvpnparser.py
ebstall/tests/test_osutils.py
ebstall/tests/test_sysctlparser.py
ebstall/tests/test_utils.py
ebstall/tests/test_versions.py
ebstall/tests/data/yum_update_list
ebstall/tools/__init__.py
ebstall/tools/versions_yaql.py