Metadata-Version: 1.1
Name: ebstall
Version: 1.3.0
Summary: Enigma Bridge Installer
Home-page: https://github.com/EnigmaBridge/ebstall.py
Author: Enigma Bridge
Author-email: info@enigmabridge.com
License: MIT License
